setup.py
pandas_rs/__init__.py
pandas_rs/rs.py
pandas_rs/version.py
pandas_rs.egg-info/PKG-INFO
pandas_rs.egg-info/SOURCES.txt
pandas_rs.egg-info/dependency_links.txt
pandas_rs.egg-info/requires.txt
pandas_rs.egg-info/top_level.txt