Metadata-Version: 1.1
Name: pandas-rs
Version: 0.1.6
Summary: pandas extension for PostgreSQL and AWS RedShift (Not Officail library)
Home-page: https://github.com/SamuraiT/pandas-rs
Author: Tatsuro Yasukawa
Author-email: t.yasukawa01@gmail.com
License: UNKNOWN
Keywords: pandas,PostgreSQL,RedShift,sql
Platform: UNKNOWN
Classifier: Programming Language :: Python
Classifier: Programming Language :: Python :: 3
Classifier: Development Status :: 4 - Beta
Classifier: Environment :: Other Environment
Classifier: Intended Audience :: Developers
Classifier: License :: OSI Approved :: MIT License
Classifier: Topic :: Software Development :: Libraries :: Python Modules
